{
  "uid": "efoq5r3c8tzb4e",
  "name": "Azslurm Dashboard Buttons",
  "kind": 1,
  "model": {
    "type": "text",
    "title": "",
    "transparent": true,
    "fieldConfig": {
      "defaults": {},
      "overrides": []
    },
    "options": {
      "code": {
        "language": "plaintext",
        "showLineNumbers": false,
        "showMiniMap": false
      },
      "content": "<div style=\"display: flex; gap: 16px; flex-wrap: wrap; margin-top: 10px; justify-content: center\">\n\n    <a href=\"/d/dfoq4uv3akf7kf/azslurm-cluster-dashboard?orgId=1&${__url_time_range}&${partition:queryparam}&${cluster:queryparam}&${instance:queryparam}&${cpu:queryparam}&${gpu:queryparam}&${nodearray:queryparam}\" \n     style=\"\n       padding: 12px 24px;\n       background: #3b3f45;\n       color: white;\n       border-radius: 8px;\n       text-decoration: none;\n       font-weight: 500;\n       box-shadow: 0 2px 6px rgba(0,0,0,0.2);\n       transition: all 0.2s ease;\n     \">\n    Slurm Cluster Overview\n  </a>\n  <a href=\"/d/dfoq4wdpomuioc/azslurm-job-and-node-status-dashboard?orgId=1&${__url_time_range}&${partition:queryparam}&${cluster:queryparam}&${instance:queryparam}&${cpu:queryparam}&${gpu:queryparam}&${nodearray:queryparam}\" \n     style=\"\n       padding: 12px 24px;\n       background: #3b3f45;\n       color: white;\n       border-radius: 8px;\n       text-decoration: none;\n       font-weight: 500;\n       box-shadow: 0 2px 6px rgba(0,0,0,0.2);\n       transition: all 0.2s ease;\n     \">\n    Slurm Job and Node Status\n  </a>\n  <a href=\"/d/afoq4ywq4lj40f/azslurm-extra-details-dashboard?orgId=1&${__url_time_range}&${partition:queryparam}&${cluster:queryparam}&${instance:queryparam}&${cpu:queryparam}&${gpu:queryparam}&${nodearray:queryparam}\" \n     style=\"\n       padding: 12px 24px;\n       background: #3b3f45;\n       color: white;\n       border-radius: 8px;\n       text-decoration: none;\n       font-weight: 500;\n       box-shadow: 0 2px 6px rgba(0,0,0,0.2);\n       transition: all 0.2s ease;\n     \">\n    Slurm Node Details\n  </a>\n\n</div>",
      "mode": "html"
    },
    "pluginVersion": "11.6.9"
  }
}
